{"הסתברות.rar":0,"1.pdf":1,"ex1_2003.pdf":2,"ex1s_2003.pdf":3,"הסתברות - תרגילים פתרונות ונוסחאות.pdf":4,"hitpalguyot.pdf":5,"הסתברות הרצאות.zip":6,"הסתברות תרגולים.zip":7,"הסתברות תרגול 7 אלבינה.pdf":8,"הסתברות הרצאה 6.pdf":9,"הסתברות הרצאה 7.pdf":10,"הסתברות תרגול 8.pdf":11,"הסתברות הרצאה 8.pdf":12,"הסתברות תרגול 9.pdf":13,"הסתברות תרגול 10.pdf":14,"הסתברות הרצאה 9.pdf":15,"הסתברות תרגול 11.pdf":16,"הסתברות 10.pdf":17,"הסתברות הרצאה 11.pdf":18,"הסתברות תרגול 12.pdf":19,"albina.pdf":20," בהסתברות.pdf":21}